sepa_sctinst/__init__.py
sepa_sctinst/default_messages.py
sepa_sctinst/message.py
sepa_sctinst/participant.py
sepa_sctinst/schema_validation.py
sepa_sctinst/sct_inst_c2b.py
sepa_sctinst/sct_inst_interbank.py
sepa_sctinst-0.0.2.dist-info/LICENSE
sepa_sctinst-0.0.2.dist-info/METADATA
sepa_sctinst-0.0.2.dist-info/WHEEL
sepa_sctinst-0.0.2.dist-info/top_level.txt
sepa_sctinst-0.0.2.dist-info/RECORD
