Metadata-Version: 2.1
Name: sepa-sctinst
Version: 0.0.2
Summary: SEPA SCTInst is a python package that provides some features to manage SCTInst payments
Home-page: https://github.com/lquastana/sepa-sctinst
Author: lquastana
License: Apache 2.0
Keywords: sepa sctinst
Platform: any
Classifier: Development Status :: 3 - Alpha
Classifier: Intended Audience :: Developers
Classifier: Operating System :: OS Independent
Classifier: Programming Language :: Python :: 3
Classifier: Topic :: Software Development :: Libraries :: Python Modules
License-File: LICENSE
Requires-Dist: lxml
Requires-Dist: Faker
Provides-Extra: dev
Requires-Dist: requests-mock ; extra == 'dev'
